verbcl_elastic/__init__.py
verbcl_elastic/__main__.py
verbcl_elastic/py.typed
verbcl_elastic-0.4.0.dist-info/entry_points.txt
verbcl_elastic-0.4.0.dist-info/LICENSE.rst
verbcl_elastic-0.4.0.dist-info/WHEEL
verbcl_elastic-0.4.0.dist-info/METADATA
verbcl_elastic-0.4.0.dist-info/RECORD
