Metadata-Version: 2.1
Name: verbcl-elastic
Version: 0.4.0
Summary: VerbCL Elastic
Home-page: https://github.com/j-rossi-nl/verbcl-elastic
License: MIT
Author: Julien Rossi
Author-email: j.rossi@uva.nl
Requires-Python: >=3.6.1,<4.0.0
Classifier: Development Status :: 4 - Beta
Classifier: License :: OSI Approved :: MIT License
Classifier: Programming Language :: Python :: 3
Classifier: Programming Language :: Python :: 3.10
Classifier: Programming Language :: Python :: 3.6
Classifier: Programming Language :: Python :: 3.7
Classifier: Programming Language :: Python :: 3.8
Classifier: Programming Language :: Python :: 3.9
Requires-Dist: click (>=8.0.1,<9.0.0)
Requires-Dist: elasticsearch (>=7.15.0,<8.0.0)
Requires-Dist: elasticsearch-dsl (>=7.4.0,<8.0.0)
Project-URL: Changelog, https://github.com/j-rossi-nl/verbcl-elastic/releases
Project-URL: Documentation, https://verbcl-elastic.readthedocs.io
Project-URL: Repository, https://github.com/j-rossi-nl/verbcl-elastic
